simplechain/__init__.py
simplechain/utils.py
simplechain/pipeline/__init__.py
simplechain/pipeline/module.py
simplechain/pipeline/standard_modules.py
simplechain/pipeline/data_loaders/__init__.py
simplechain/pipeline/data_loaders/user_input.py
simplechain/pipeline/prompt_templates/__init__.py
simplechain/pipeline/prompt_templates/base_template.py
simplechain/pipeline/prompt_templates/conversation_prompts.py
simplechain/pipeline/prompt_templates/database_prompts.py
simplechain/pipeline/providers/__init__.py
simplechain/pipeline/providers/database.py
simplechain/pipeline/providers/search.py
simplechain/stack/__init__.py
simplechain/stack/factory.py
simplechain/stack/databases/__init__.py
simplechain/stack/databases/base.py
simplechain/stack/databases/sql.py
simplechain/stack/image_generators/__init__.py
simplechain/stack/pdf_loaders/__init__.py
simplechain/stack/pdf_loaders/base.py
simplechain/stack/search_engines/__init__.py
simplechain/stack/search_engines/base.py
simplechain/stack/search_engines/google_serper.py
simplechain/stack/text_embedders/__init__.py
simplechain/stack/text_embedders/ai21.py
simplechain/stack/text_embedders/base.py
simplechain/stack/text_embedders/openai.py
simplechain/stack/text_generators/__init__.py
simplechain/stack/text_generators/base.py
simplechain/stack/text_generators/llms/__init__.py
simplechain/stack/text_generators/llms/ai21.py
simplechain/stack/text_generators/llms/llm.py
simplechain/stack/text_generators/llms/openai.py
simplechain/stack/vector_databases/__init__.py
simplechain/stack/vector_databases/annoy.py
simplechain/stack/vector_databases/annoy_vd.py
simplechain/stack/vector_databases/base.py
simplechain/stack/vector_databases/faiss.py
tests/__init__.py
simplechain-0.0.5.7.dist-info/LICENSE
simplechain-0.0.5.7.dist-info/METADATA
simplechain-0.0.5.7.dist-info/WHEEL
simplechain-0.0.5.7.dist-info/top_level.txt
simplechain-0.0.5.7.dist-info/RECORD
