Metadata-Version: 2.1
Name: simplechain
Version: 0.0.5.7
Summary: A package of AI services in modular form
Author: Rahel Gunaratne
Author-email: rahel.gunaratne@gmail.com
Keywords: python,first package
Classifier: Development Status :: 3 - Alpha
Classifier: Intended Audience :: Education
Classifier: Programming Language :: Python :: 2
Classifier: Programming Language :: Python :: 3
Classifier: Operating System :: MacOS :: MacOS X
Classifier: Operating System :: Microsoft :: Windows
License-File: LICENSE
